pyxelxl-0.0.18.dist-info/METADATA
pyxelxl-0.0.18.dist-info/WHEEL
pyxelxl.libs/libgcc_s-e52197c3.so.1
pyxelxl/py.typed
pyxelxl/rotate.py
pyxelxl/font.py
pyxelxl/pyxelxl.pyi
pyxelxl/__init__.py
pyxelxl/pyxelxl.abi3.so
pyxelxl-0.0.18.dist-info/RECORD
