Metadata-Version: 2.3
Name: pyxelxl
Version: 0.0.18
Classifier: Programming Language :: Rust
Classifier: Programming Language :: Python :: Implementation :: CPython
Classifier: Programming Language :: Python :: Implementation :: PyPy
Requires-Dist: pyxel >=2.0.0
Requires-Dist: numpy ~=1.25.0
Summary: Truetype fonts, sprite rotation, and in the future more extensions for Pyxel.
Author-email: RuneBlaze <runeblaze@protonmail.com>
Requires-Python: >=3.7
